.flake8
LICENSE
MANIFEST.in
README.md
create_analysis.sh
law.cfg
setup.py
setup.sh
bin/cf_create_venv
bin/cf_diff
bin/cf_diff.py
bin/cf_inspect
bin/cf_inspect.py
bin/cf_make_venv_relocatable
bin/cf_remove_wlcg_cache_locks
bin/cf_sandbox
bin/cf_sandbox_file_hash
bin/cf_sandbox_file_hash.py
bin/cf_update_submodules
bin/law
bin/githooks/combined_hook.sh
bin/githooks/post-commit
columnflow/__init__.py
columnflow/__version__.py
columnflow/columnar_util.py
columnflow/config_util.py
columnflow/types.py
columnflow/util.py
columnflow.egg-info/PKG-INFO
columnflow.egg-info/SOURCES.txt
columnflow.egg-info/dependency_links.txt
columnflow.egg-info/not-zip-safe
columnflow.egg-info/requires.txt
columnflow.egg-info/top_level.txt
columnflow/calibration/__init__.py
columnflow/calibration/util.py
columnflow/calibration/cms/__init__.py
columnflow/calibration/cms/jets.py
columnflow/calibration/cms/jets_coffea.py
columnflow/calibration/cms/met.py
columnflow/calibration/cms/tau.py
columnflow/categorization/__init__.py
columnflow/inference/__init__.py
columnflow/inference/cms/__init__.py
columnflow/inference/cms/datacard.py
columnflow/ml/__init__.py
columnflow/plotting/__init__.py
columnflow/plotting/plot_all.py
columnflow/plotting/plot_functions_1d.py
columnflow/plotting/plot_functions_2d.py
columnflow/plotting/plot_ml_evaluation.py
columnflow/plotting/plot_util.py
columnflow/production/__init__.py
columnflow/production/categories.py
columnflow/production/normalization.py
columnflow/production/processes.py
columnflow/production/util.py
columnflow/production/cms/__init__.py
columnflow/production/cms/btag.py
columnflow/production/cms/electron.py
columnflow/production/cms/gen_top_decay.py
columnflow/production/cms/mc_weight.py
columnflow/production/cms/muon.py
columnflow/production/cms/pdf.py
columnflow/production/cms/pileup.py
columnflow/production/cms/scale.py
columnflow/production/cms/seeds.py
columnflow/production/cms/top_pt_weight.py
columnflow/selection/__init__.py
columnflow/selection/empty.py
columnflow/selection/matching.py
columnflow/selection/stats.py
columnflow/selection/util.py
columnflow/selection/cms/__init__.py
columnflow/selection/cms/jets.py
