Metadata-Version: 2.1
Name: columnflow
Version: 0.2.4
Summary: columnflow
Home-page: https://github.com/columnflow/columnflow
Author: The columnflow team
Author-email: github.riga@icloud.com
License: BSD-3-Clause
Keywords: physics,analysis,experiment,columnar,vectorized,law,order,luigi,workflow,automation,lhc,cern
Platform: UNKNOWN
Classifier: Programming Language :: Python
Classifier: Programming Language :: Python :: 3
Classifier: Programming Language :: Python :: 3.7
Classifier: Programming Language :: Python :: 3.8
Classifier: Programming Language :: Python :: 3.9
Classifier: Programming Language :: Python :: 3.10
Classifier: Programming Language :: Python :: 3.11
Classifier: Development Status :: 4 - Beta
Classifier: Operating System :: OS Independent
Classifier: License :: OSI Approved :: BSD License
Classifier: Intended Audience :: Developers
Classifier: Intended Audience :: Science/Research
Classifier: Intended Audience :: Information Technology
Requires-Python: >=3.7, <=3.11
License-File: LICENSE
